btrccts/__init__.py
btrccts/algorithm.py
btrccts/async_exchange.py
btrccts/balance.py
btrccts/check_dataframe.py
btrccts/context.py
btrccts/convert_float.py
btrccts/exchange.py
btrccts/exchange_account.py
btrccts/exchange_backend.py
btrccts/run.py
btrccts/timeframe.py
btrccts-0.1.4.dist-info/LICENSE.txt
btrccts-0.1.4.dist-info/METADATA
btrccts-0.1.4.dist-info/WHEEL
btrccts-0.1.4.dist-info/entry_points.txt
btrccts-0.1.4.dist-info/top_level.txt
btrccts-0.1.4.dist-info/RECORD
