Metadata-Version: 2.1
Name: btrccts
Version: 0.1.4
Summary: BackTest and Run CryptoCurrency Trading Strategies
Home-page: https://github.com/btrccts/btrccts/
Author: Simon Brand
Author-email: simon.brand@postadigitale.de
Keywords: btrccts
Classifier: Programming Language :: Python
Classifier: Intended Audience :: Developers
Classifier: Intended Audience :: Financial and Insurance Industry
Classifier: Topic :: Software Development :: Build Tools
Classifier: Topic :: Office/Business :: Financial :: Investment
Classifier: License :: OSI Approved :: MIT License
Classifier: Programming Language :: Python :: 3
Classifier: Programming Language :: Python :: 3.9
Classifier: Programming Language :: Python :: 3.10
Classifier: Programming Language :: Python :: 3.11
Classifier: Programming Language :: Python :: 3.12
Classifier: Operating System :: OS Independent
Classifier: Environment :: Console
License-File: LICENSE.txt
Requires-Dist: appdirs
Requires-Dist: ccxt
Requires-Dist: numpy
Requires-Dist: pandas
Provides-Extra: ccxt-websockets
Requires-Dist: ccxtpro ; extra == 'ccxt-websockets'
Provides-Extra: dev
Requires-Dist: pycodestyle ; extra == 'dev'
Requires-Dist: pyflakes ; extra == 'dev'
